{
  "e8022556f2eda60799c68bbd339967cd" : {
    "statistic" : {
      "failed" : 0,
      "broken" : 0,
      "skipped" : 0,
      "passed" : 1,
      "unknown" : 0,
      "total" : 1
    },
    "items" : [ {
      "uid" : "634cbe9690394a61",
      "reportUrl" : "https://nikithapreethamsonos.github.io/gitactions_test/37//#testresult/634cbe9690394a61",
      "status" : "passed",
      "time" : {
        "start" : 1682106033518,
        "stop" : 1682106035666,
        "duration" : 2148
      }
    } ]
  },
  "54924dbd39741d2b1fb17a1e850e4774" : {
    "statistic" : {
      "failed" : 0,
      "broken" : 0,
      "skipped" : 0,
      "passed" : 1,
      "unknown" : 0,
      "total" : 1
    },
    "items" : [ {
      "uid" : "b6b4f9535df55769",
      "reportUrl" : "https://nikithapreethamsonos.github.io/gitactions_test/37//#testresult/b6b4f9535df55769",
      "status" : "passed",
      "time" : {
        "start" : 1682106116093,
        "stop" : 1682106116209,
        "duration" : 116
      }
    } ]
  },
  "1b7254d6d5fcd23e8c2c401a68237290" : {
    "statistic" : {
      "failed" : 0,
      "broken" : 0,
      "skipped" : 0,
      "passed" : 1,
      "unknown" : 0,
      "total" : 1
    },
    "items" : [ {
      "uid" : "4bf75b7b7eb88b3b",
      "reportUrl" : "https://nikithapreethamsonos.github.io/gitactions_test/37//#testresult/4bf75b7b7eb88b3b",
      "status" : "passed",
      "time" : {
        "start" : 1682106078751,
        "stop" : 1682106089000,
        "duration" : 10249
      }
    } ]
  },
  "c49d7ecb157cc228a16e2a223de57143" : {
    "statistic" : {
      "failed" : 0,
      "broken" : 0,
      "skipped" : 0,
      "passed" : 1,
      "unknown" : 0,
      "total" : 1
    },
    "items" : [ {
      "uid" : "a5ef476508e01c72",
      "reportUrl" : "https://nikithapreethamsonos.github.io/gitactions_test/37//#testresult/a5ef476508e01c72",
      "status" : "passed",
      "time" : {
        "start" : 1682106119759,
        "stop" : 1682106154254,
        "duration" : 34495
      }
    } ]
  },
  "3c296e3995b479bb8e89ce4c9b6a2f9a" : {
    "statistic" : {
      "failed" : 0,
      "broken" : 0,
      "skipped" : 0,
      "passed" : 1,
      "unknown" : 0,
      "total" : 1
    },
    "items" : [ {
      "uid" : "4c67b03402aa0e9b",
      "reportUrl" : "https://nikithapreethamsonos.github.io/gitactions_test/37//#testresult/4c67b03402aa0e9b",
      "status" : "passed",
      "time" : {
        "start" : 1682106050701,
        "stop" : 1682106052873,
        "duration" : 2172
      }
    } ]
  },
  "89cada7405fecc699b6cf500c5cb146b" : {
    "statistic" : {
      "failed" : 0,
      "broken" : 0,
      "skipped" : 0,
      "passed" : 1,
      "unknown" : 0,
      "total" : 1
    },
    "items" : [ {
      "uid" : "d0fb7fda6dea03d7",
      "reportUrl" : "https://nikithapreethamsonos.github.io/gitactions_test/37//#testresult/d0fb7fda6dea03d7",
      "status" : "passed",
      "time" : {
        "start" : 1682106061538,
        "stop" : 1682106063684,
        "duration" : 2146
      }
    } ]
  },
  "1835dc184cf9f37092327c770708733d" : {
    "statistic" : {
      "failed" : 0,
      "broken" : 0,
      "skipped" : 0,
      "passed" : 1,
      "unknown" : 0,
      "total" : 1
    },
    "items" : [ {
      "uid" : "1edb76dba0eb7d1d",
      "reportUrl" : "https://nikithapreethamsonos.github.io/gitactions_test/37//#testresult/1edb76dba0eb7d1d",
      "status" : "passed",
      "time" : {
        "start" : 1682106039189,
        "stop" : 1682106041328,
        "duration" : 2139
      }
    } ]
  },
  "578a17f8bcc9ae11155a4eefba8c0465" : {
    "statistic" : {
      "failed" : 0,
      "broken" : 0,
      "skipped" : 1,
      "passed" : 0,
      "unknown" : 0,
      "total" : 1
    },
    "items" : [ {
      "uid" : "bb562e8e19520b5e",
      "reportUrl" : "https://nikithapreethamsonos.github.io/gitactions_test/37//#testresult/bb562e8e19520b5e",
      "status" : "skipped",
      "statusDetails" : "Skipped: SIMULATOR_SKIP: Skipped because simulators rely on the media container, not the camb-nas share.",
      "time" : {
        "start" : 1682106155005,
        "stop" : 1682106155005,
        "duration" : 0
      }
    } ]
  },
  "85d615623b2f2e8e818cdd827e9b4dac" : {
    "statistic" : {
      "failed" : 0,
      "broken" : 0,
      "skipped" : 0,
      "passed" : 1,
      "unknown" : 0,
      "total" : 1
    },
    "items" : [ {
      "uid" : "68263ac021df0f04",
      "reportUrl" : "https://nikithapreethamsonos.github.io/gitactions_test/37//#testresult/68263ac021df0f04",
      "status" : "passed",
      "time" : {
        "start" : 1682106103213,
        "stop" : 1682106104238,
        "duration" : 1025
      }
    } ]
  },
  "ec39d5e7d400e11db79619f9ebd3c3c0" : {
    "statistic" : {
      "failed" : 0,
      "broken" : 0,
      "skipped" : 0,
      "passed" : 1,
      "unknown" : 0,
      "total" : 1
    },
    "items" : [ {
      "uid" : "cee78784b7813802",
      "reportUrl" : "https://nikithapreethamsonos.github.io/gitactions_test/37//#testresult/cee78784b7813802",
      "status" : "passed",
      "time" : {
        "start" : 1682106106501,
        "stop" : 1682106109716,
        "duration" : 3215
      }
    } ]
  },
  "e6c2253eff0ae0c9cfd309e71df99364" : {
    "statistic" : {
      "failed" : 0,
      "broken" : 0,
      "skipped" : 0,
      "passed" : 1,
      "unknown" : 0,
      "total" : 1
    },
    "items" : [ {
      "uid" : "e619de5433663615",
      "reportUrl" : "https://nikithapreethamsonos.github.io/gitactions_test/37//#testresult/e619de5433663615",
      "status" : "passed",
      "time" : {
        "start" : 1682106067232,
        "stop" : 1682106069378,
        "duration" : 2146
      }
    } ]
  },
  "b9c5045802273ea1bb019e2163503138" : {
    "statistic" : {
      "failed" : 0,
      "broken" : 0,
      "skipped" : 0,
      "passed" : 1,
      "unknown" : 0,
      "total" : 1
    },
    "items" : [ {
      "uid" : "2e02d40a6b71f116",
      "reportUrl" : "https://nikithapreethamsonos.github.io/gitactions_test/37//#testresult/2e02d40a6b71f116",
      "status" : "passed",
      "time" : {
        "start" : 1682106112663,
        "stop" : 1682106114039,
        "duration" : 1376
      }
    } ]
  },
  "29cae695e2fb26b9ca5c905c53800dbc" : {
    "statistic" : {
      "failed" : 0,
      "broken" : 0,
      "skipped" : 0,
      "passed" : 1,
      "unknown" : 0,
      "total" : 1
    },
    "items" : [ {
      "uid" : "c283270692e2c08c",
      "reportUrl" : "https://nikithapreethamsonos.github.io/gitactions_test/37//#testresult/c283270692e2c08c",
      "status" : "passed",
      "time" : {
        "start" : 1682106016632,
        "stop" : 1682106018780,
        "duration" : 2148
      }
    } ]
  },
  "0a850759951f0be298e192310c5b52db" : {
    "statistic" : {
      "failed" : 0,
      "broken" : 0,
      "skipped" : 0,
      "passed" : 1,
      "unknown" : 0,
      "total" : 1
    },
    "items" : [ {
      "uid" : "b1f517ca6005d33b",
      "reportUrl" : "https://nikithapreethamsonos.github.io/gitactions_test/37//#testresult/b1f517ca6005d33b",
      "status" : "passed",
      "time" : {
        "start" : 1682106045095,
        "stop" : 1682106047251,
        "duration" : 2156
      }
    } ]
  },
  "0cba8f3fc4b36041ef176a3f3a69f60f" : {
    "statistic" : {
      "failed" : 0,
      "broken" : 0,
      "skipped" : 0,
      "passed" : 1,
      "unknown" : 0,
      "total" : 1
    },
    "items" : [ {
      "uid" : "ec471998ba612ca7",
      "reportUrl" : "https://nikithapreethamsonos.github.io/gitactions_test/37//#testresult/ec471998ba612ca7",
      "status" : "passed",
      "time" : {
        "start" : 1682106027890,
        "stop" : 1682106030153,
        "duration" : 2263
      }
    } ]
  },
  "13ba8f5f06121e49ffa4cbc8841f628c" : {
    "statistic" : {
      "failed" : 0,
      "broken" : 0,
      "skipped" : 0,
      "passed" : 1,
      "unknown" : 0,
      "total" : 1
    },
    "items" : [ {
      "uid" : "3d74af3fdf774beb",
      "reportUrl" : "https://nikithapreethamsonos.github.io/gitactions_test/37//#testresult/3d74af3fdf774beb",
      "status" : "passed",
      "time" : {
        "start" : 1682106022286,
        "stop" : 1682106024439,
        "duration" : 2153
      }
    } ]
  },
  "524f7ac83bd02a52123e17611f3cdabd" : {
    "statistic" : {
      "failed" : 0,
      "broken" : 0,
      "skipped" : 0,
      "passed" : 1,
      "unknown" : 0,
      "total" : 1
    },
    "items" : [ {
      "uid" : "7ec8f1b19c6b3de1",
      "reportUrl" : "https://nikithapreethamsonos.github.io/gitactions_test/37//#testresult/7ec8f1b19c6b3de1",
      "status" : "passed",
      "time" : {
        "start" : 1682106056151,
        "stop" : 1682106058304,
        "duration" : 2153
      }
    } ]
  },
  "3f869609f499f0bd1da6ba19961323a6" : {
    "statistic" : {
      "failed" : 0,
      "broken" : 0,
      "skipped" : 1,
      "passed" : 0,
      "unknown" : 0,
      "total" : 1
    },
    "items" : [ {
      "uid" : "de305e39e8633161",
      "reportUrl" : "https://nikithapreethamsonos.github.io/gitactions_test/37//#testresult/de305e39e8633161",
      "status" : "skipped",
      "statusDetails" : "Skipped: SIMULATOR_SKIP: Skipped because simulators rely on the media container, not the camb-nas share.",
      "time" : {
        "start" : 1682106155089,
        "stop" : 1682106155089,
        "duration" : 0
      }
    } ]
  },
  "58e03872a2fa0290aa1e9f2e845607bc" : {
    "statistic" : {
      "failed" : 0,
      "broken" : 0,
      "skipped" : 0,
      "passed" : 1,
      "unknown" : 0,
      "total" : 1
    },
    "items" : [ {
      "uid" : "de33c8bf3e78e570",
      "reportUrl" : "https://nikithapreethamsonos.github.io/gitactions_test/37//#testresult/de33c8bf3e78e570",
      "status" : "passed",
      "time" : {
        "start" : 1682106072886,
        "stop" : 1682106075038,
        "duration" : 2152
      }
    } ]
  },
  "38444c15f1b869315b699f2ece851718" : {
    "statistic" : {
      "failed" : 0,
      "broken" : 0,
      "skipped" : 0,
      "passed" : 1,
      "unknown" : 0,
      "total" : 1
    },
    "items" : [ {
      "uid" : "82046719ca6caba1",
      "reportUrl" : "https://nikithapreethamsonos.github.io/gitactions_test/37//#testresult/82046719ca6caba1",
      "status" : "passed",
      "time" : {
        "start" : 1682106092356,
        "stop" : 1682106093361,
        "duration" : 1005
      }
    } ]
  },
  "e24b2336d4a3465ca17fc95aeb613c4e" : {
    "statistic" : {
      "failed" : 0,
      "broken" : 0,
      "skipped" : 1,
      "passed" : 0,
      "unknown" : 0,
      "total" : 1
    },
    "items" : [ {
      "uid" : "20ace4d5bc7215b3",
      "reportUrl" : "https://nikithapreethamsonos.github.io/gitactions_test/37//#testresult/20ace4d5bc7215b3",
      "status" : "skipped",
      "statusDetails" : "Skipped: SIMULATOR_SKIP: Skipped because simulators rely on the media container, not the camb-nas share.",
      "time" : {
        "start" : 1682106155085,
        "stop" : 1682106155085,
        "duration" : 0
      }
    } ]
  },
  "8cb90a396a024fd4fcc5c0a0afc1c7d4" : {
    "statistic" : {
      "failed" : 0,
      "broken" : 0,
      "skipped" : 1,
      "passed" : 0,
      "unknown" : 0,
      "total" : 1
    },
    "items" : [ {
      "uid" : "dcf60d3d03a265c",
      "reportUrl" : "https://nikithapreethamsonos.github.io/gitactions_test/37//#testresult/dcf60d3d03a265c",
      "status" : "skipped",
      "statusDetails" : "Skipped: SIMULATOR_SKIP: Skipped because simulators rely on the media container, not the camb-nas share.",
      "time" : {
        "start" : 1682106155093,
        "stop" : 1682106155093,
        "duration" : 0
      }
    } ]
  },
  "4e1a89fdbc88b461e978627bed80323d" : {
    "statistic" : {
      "failed" : 0,
      "broken" : 0,
      "skipped" : 0,
      "passed" : 1,
      "unknown" : 0,
      "total" : 1
    },
    "items" : [ {
      "uid" : "149a6f98bb280d22",
      "reportUrl" : "https://nikithapreethamsonos.github.io/gitactions_test/37//#testresult/149a6f98bb280d22",
      "status" : "passed",
      "time" : {
        "start" : 1682106010319,
        "stop" : 1682106012468,
        "duration" : 2149
      }
    } ]
  }
}